README.md
setup.py
tests/resources/__init__.py
tests/zilliqaetl/__init__.py
tests/zilliqaetl/helpers.py
tests/zilliqaetl/mock_zilliqa_api.py
zilliqa_etl.egg-info/PKG-INFO
zilliqa_etl.egg-info/SOURCES.txt
zilliqa_etl.egg-info/dependency_links.txt
zilliqa_etl.egg-info/entry_points.txt
zilliqa_etl.egg-info/requires.txt
zilliqa_etl.egg-info/top_level.txt
zilliqaetl/__init__.py
zilliqaetl/__main__.py
zilliqaetl/cli/__init__.py
zilliqaetl/cli/export_ds_blocks.py
zilliqaetl/cli/export_tx_blocks.py
zilliqaetl/cli/get_ds_block_range_for_date.py
zilliqaetl/cli/get_tx_block_range_for_date.py
zilliqaetl/cli/rate_limiting_proxy.py
zilliqaetl/exporters/__init__.py
zilliqaetl/exporters/zilliqa_item_exporter.py
zilliqaetl/jobs/__init__.py
zilliqaetl/jobs/export_ds_blocks_job.py
zilliqaetl/jobs/export_tx_blocks_job.py
zilliqaetl/jobs/retriable_exceptions.py
zilliqaetl/mappers/__init__.py
zilliqaetl/mappers/ds_block_mapper.py
zilliqaetl/mappers/event_log_mapper.py
zilliqaetl/mappers/exception_mapper.py
zilliqaetl/mappers/transaction_mapper.py
zilliqaetl/mappers/transition_mapper.py
zilliqaetl/mappers/tx_block_mapper.py
zilliqaetl/service/__init__.py
zilliqaetl/service/block_range_service.py
zilliqaetl/service/ds_block_timestamp_graph.py
zilliqaetl/service/tx_block_timestamp_graph.py
zilliqaetl/service/zilliqa_service.py
zilliqaetl/utils/__init__.py
zilliqaetl/utils/zilliqa_utils.py